fusio_sdk-6.4.1.dist-info/licenses/LICENSE
sdk/authorization_tag.py
sdk/backend_account_change_password.py
sdk/backend_account_tag.py
sdk/backend_action.py
sdk/backend_action_collection.py
sdk/backend_action_config.py
sdk/backend_action_create.py
sdk/backend_action_execute_request.py
sdk/backend_action_execute_request_body.py
sdk/backend_action_execute_response.py
sdk/backend_action_execute_response_body.py
sdk/backend_action_execute_response_headers.py
sdk/backend_action_index.py
sdk/backend_action_index_entry.py
sdk/backend_action_tag.py
sdk/backend_action_update.py
sdk/backend_agent.py
sdk/backend_agent_collection.py
sdk/backend_agent_message.py
sdk/backend_agent_message_binary.py
sdk/backend_agent_message_choice.py
sdk/backend_agent_message_object.py
sdk/backend_agent_message_text.py
sdk/backend_agent_message_tool_call.py
sdk/backend_agent_message_tool_call_function.py
sdk/backend_agent_request.py
sdk/backend_agent_response.py
sdk/backend_app.py
sdk/backend_app_collection.py
sdk/backend_app_create.py
sdk/backend_app_tag.py
sdk/backend_app_update.py
sdk/backend_audit.py
sdk/backend_audit_collection.py
sdk/backend_audit_object.py
sdk/backend_audit_tag.py
sdk/backend_backup_export.py
sdk/backend_backup_import.py
sdk/backend_backup_import_result.py
sdk/backend_backup_tag.py
sdk/backend_bundle.py
sdk/backend_bundle_collection.py
sdk/backend_bundle_config.py
sdk/backend_bundle_create.py
sdk/backend_bundle_tag.py
sdk/backend_bundle_update.py
sdk/backend_category.py
sdk/backend_category_collection.py
sdk/backend_category_create.py
sdk/backend_category_tag.py
sdk/backend_category_update.py
sdk/backend_config.py
sdk/backend_config_collection.py
sdk/backend_config_tag.py
sdk/backend_config_update.py
sdk/backend_connection.py
sdk/backend_connection_agent_tag.py
sdk/backend_connection_collection.py
sdk/backend_connection_config.py
sdk/backend_connection_create.py
sdk/backend_connection_database_tag.py
sdk/backend_connection_filesystem_tag.py
sdk/backend_connection_http_tag.py
sdk/backend_connection_index.py
fusio_sdk-6.4.1.dist-info/METADATA
fusio_sdk-6.4.1.dist-info/WHEEL
fusio_sdk-6.4.1.dist-info/top_level.txt
fusio_sdk-6.4.1.dist-info/RECORD
