Metadata-Version: 2.4
Name: fusio-sdk
Version: 6.4.1
Summary: SDK to talk to the Fusio REST API
Author-email: Christoph Kappestein <christoph.kappestein@gmail.com>
License: MIT
Project-URL: Homepage, https://github.com/apioo/fusio-sdk-python
Project-URL: Issues, https://github.com/apioo/fusio-sdk-sdkgen-python/issues
Classifier: Programming Language :: Python :: 3
Classifier: License :: OSI Approved :: MIT License
Classifier: Operating System :: OS Independent
Classifier: Topic :: Software Development :: Code Generators
Requires-Python: >=3.8
License-File: LICENSE
Requires-Dist: sdkgen-client>=2.0.1
Dynamic: license-file
